lines_dataset/__init__.py
lines_dataset/__init__.pyi
lines_dataset/cli.py
lines_dataset/compression.py
lines_dataset/dataset.py
lines_dataset/meta.py
lines_dataset-0.2.9.dist-info/METADATA
lines_dataset-0.2.9.dist-info/WHEEL
lines_dataset-0.2.9.dist-info/entry_points.txt
lines_dataset-0.2.9.dist-info/top_level.txt
lines_dataset-0.2.9.dist-info/RECORD
