Metadata-Version: 2.1
Name: lines-dataset
Version: 0.2.9
Summary: Dead simple standard for storing/loading datasets as lines of text. Supports zstd compression.
Author-email: Marcel Claramunt <marcel@moveread.com>
Project-URL: repo, https://github.com/marciclabas/mltools.git
Requires-Python: >=3.10
Requires-Dist: pydantic
Requires-Dist: haskellian
Provides-Extra: cli
Requires-Dist: typer ; extra == 'cli'
